{
  "$schema": "https://developer.microsoft.com/json-schemas/fabric/item/report/definition/visualContainer/2.4.0/schema.json",
  "name": "1f90c3dfab07a5227e7a",
  "position": {
    "x": 21.569303560737563,
    "y": 73.642587841941847,
    "z": 23000,
    "height": 47.340612891863337,
    "width": 126.80521310320536,
    "tabOrder": 23000
  },
  "visual": {
    "visualType": "textbox",
    "objects": {
      "general": [
        {
          "properties": {
            "paragraphs": [
              {
                "textRuns": [
                  {
                    "value": "Filters",
                    "textStyle": {
                      "fontFamily": "Segoe (Bold)",
                      "fontSize": "20pt",
                      "color": "#ffffff"
                    }
                  }
                ],
                "horizontalTextAlignment": "center"
              }
            ]
          }
        }
      ]
    },
    "drillFilterOtherVisuals": true
  }
}